odoo8_addon_purchase_requisition_auto_rfq_bid_selection-8.0.0.1.0.99.dev4-py2.7-nspkg.pth
odoo8_addon_purchase_requisition_auto_rfq_bid_selection-8.0.0.1.0.99.dev4.dist-info/DESCRIPTION.rst
odoo8_addon_purchase_requisition_auto_rfq_bid_selection-8.0.0.1.0.99.dev4.dist-info/METADATA
odoo8_addon_purchase_requisition_auto_rfq_bid_selection-8.0.0.1.0.99.dev4.dist-info/RECORD
odoo8_addon_purchase_requisition_auto_rfq_bid_selection-8.0.0.1.0.99.dev4.dist-info/WHEEL
odoo8_addon_purchase_requisition_auto_rfq_bid_selection-8.0.0.1.0.99.dev4.dist-info/metadata.json
odoo8_addon_purchase_requisition_auto_rfq_bid_selection-8.0.0.1.0.99.dev4.dist-info/namespace_packages.txt
odoo8_addon_purchase_requisition_auto_rfq_bid_selection-8.0.0.1.0.99.dev4.dist-info/top_level.txt
odoo_addons/purchase_requisition_auto_rfq_bid_selection/README.rst
odoo_addons/purchase_requisition_auto_rfq_bid_selection/__init__.py
odoo_addons/purchase_requisition_auto_rfq_bid_selection/__openerp__.py
odoo_addons/purchase_requisition_auto_rfq_bid_selection/i18n/fr.po
odoo_addons/purchase_requisition_auto_rfq_bid_selection/i18n/purchase_requisition_auto_rfq_bid_selection.pot
odoo_addons/purchase_requisition_auto_rfq_bid_selection/i18n/sl.po
odoo_addons/purchase_requisition_auto_rfq_bid_selection/model/__init__.py
odoo_addons/purchase_requisition_auto_rfq_bid_selection/model/purchase_requisition.py
odoo_addons/purchase_requisition_auto_rfq_bid_selection/static/description/icon.png
odoo_addons/purchase_requisition_auto_rfq_bid_selection/test/purchase_requisition.yml
odoo_addons/purchase_requisition_auto_rfq_bid_selection/view/purchase_requisition.xml
